Metadata-Version: 2.1
Name: loop-destroyer
Version: 0.1.0
Summary: A loop destroyer, for your personal disintegration loops.
Home-page: https://github.com/mattyonweb/loop-destroyer
Author: Jacopo Belbo
Author-email: kfgodel@autistici.org
License: UNKNOWN
Platform: UNKNOWN
Classifier: Programming Language :: Python :: 3
Classifier: Environment :: Console
Classifier: License :: OSI Approved :: GNU General Public License v3 (GPLv3)
Classifier: Topic :: Multimedia :: Sound/Audio
Requires-Python: >=3.7
